docile/__init__.py
docile/cli/__init__.py
docile/cli/evaluate.py
docile/dataset/__init__.py
docile/dataset/bbox.py
docile/dataset/cached_object.py
docile/dataset/dataset.py
docile/dataset/document.py
docile/dataset/document_annotation.py
docile/dataset/document_images.py
docile/dataset/document_ocr.py
docile/dataset/field.py
docile/dataset/paths.py
docile/dataset/table_grid.py
docile/dataset/types.py
docile/evaluation/__init__.py
docile/evaluation/average_precision.py
docile/evaluation/evaluate.py
docile/evaluation/evaluation_subsets.py
docile/evaluation/line_item_matching.py
docile/evaluation/pcc.py
docile/evaluation/pcc_field_matching.py
docile/evaluation/snap_ocr_boxes.ipynb
docile/evaluation/validate_dataset.ipynb
docile/evaluation/validate_final_dataset.ipynb
docile/tools/Untitled.ipynb
docile/tools/__init__.py
docile/tools/dataset_browser-Copy1.ipynb
docile/tools/dataset_browser.ipynb
docile/tools/dataset_browser.py
docile/tools/docile221124-3-ocr-snapped.zip
docile/tools/docile_stats.ipynb
docile/tools/docile_stats_and_figures.ipynb
docile/tools/docile_stats_milan-Copy1.ipynb
docile/tools/final_dataset_split.ipynb
docile/tools/image_size.ipynb
docile/tools/no_annotatoins.png
docile/tools/print_results.py
docile/tools/print_results.sh
docile/tools/zip_ocr.ipynb
docile_benchmark-0.3.4.dist-info/LICENSE
docile_benchmark-0.3.4.dist-info/METADATA
docile_benchmark-0.3.4.dist-info/WHEEL
docile_benchmark-0.3.4.dist-info/entry_points.txt
docile_benchmark-0.3.4.dist-info/RECORD
