Metadata-Version: 2.1
Name: docile-benchmark
Version: 0.3.4
Summary: Tools to work with the DocILE dataset and benchmark
Home-page: https://docile.rossum.ai/
Author: Stepan Simsa
Author-email: stepan.simsa@rossum.ai
Requires-Python: >=3.9,<3.13
Classifier: Programming Language :: Python :: 3
Classifier: Programming Language :: Python :: 3.9
Classifier: Programming Language :: Python :: 3.10
Classifier: Programming Language :: Python :: 3.11
Classifier: Programming Language :: Python :: 3.12
Provides-Extra: baselines
Provides-Extra: interactive
Provides-Extra: ocr
Requires-Dist: aiobotocore (>=2.12.3,<3.0.0) ; extra == "baselines"
Requires-Dist: botocore (>=1.34.69,<2.0.0) ; extra == "baselines"
Requires-Dist: click (>=8.0.0,<9.0.0)
Requires-Dist: datasets[s3] (>=2.8.0,<2.10.0) ; extra == "baselines"
Requires-Dist: ipywidgets (>=8.0.4,<9.0.0) ; extra == "interactive"
Requires-Dist: jupyterlab (>=3.5.0,<4.0.0) ; extra == "interactive"
Requires-Dist: networkx[default] (>=2.8.8,<3.0.0)
Requires-Dist: opencv-python (>=4.6.0.66,<5.0.0.0) ; extra == "ocr"
Requires-Dist: pdf2image (>=1.16.0,<2.0.0)
Requires-Dist: pillow (>=9.1.0)
Requires-Dist: plotly (>=5.12.0,<6.0.0) ; extra == "interactive"
Requires-Dist: python-doctr (>=0.6.0) ; extra == "ocr"
Requires-Dist: pytorch-lightning[extra] (>=1.8.3,<2.0.0) ; extra == "baselines"
Requires-Dist: scikit-learn (>=1.2.1,<2.0.0) ; extra == "baselines"
Requires-Dist: sentencepiece (>=0.1.97,<0.2.0) ; extra == "baselines"
Requires-Dist: tabulate (>=0.9.0,<0.10.0)
Requires-Dist: tensorboard (>=2.11.2,<3.0.0) ; extra == "baselines"
Requires-Dist: timm (>=0.6.11,<0.7.0) ; extra == "baselines"
Requires-Dist: torch (>=1.13.1) ; extra == "ocr" or extra == "baselines"
Requires-Dist: torchmetrics (>=0.11.0,<0.12.0) ; extra == "baselines"
Requires-Dist: torchvision (>=0.14.1) ; extra == "ocr" or extra == "baselines"
Requires-Dist: tqdm (>=4.64.1,<5.0.0)
Requires-Dist: transformers[torch] (>=4.26.1) ; extra == "baselines"
Project-URL: Repository, https://github.com/rossumai/docile
